site/__init__.py
site/conf.py
weblocust/__init__.py
weblocust/logging.conf
weblocust/run.py
weblocust/database/__init__.py
weblocust/database/basedb.py
weblocust/database/base/__init__.py
weblocust/database/base/projectdb.py
weblocust/database/base/resultdb.py
weblocust/database/base/taskdb.py
weblocust/database/elasticsearch/__init__.py
weblocust/database/elasticsearch/projectdb.py
weblocust/database/elasticsearch/resultdb.py
weblocust/database/elasticsearch/taskdb.py
weblocust/database/local/__init__.py
weblocust/database/local/projectdb.py
weblocust/database/mongodb/__init__.py
weblocust/database/mongodb/mongodbbase.py
weblocust/database/mongodb/projectdb.py
weblocust/database/mongodb/resultdb.py
weblocust/database/mongodb/taskdb.py
weblocust/database/mysql/__init__.py
weblocust/database/mysql/mysqlbase.py
weblocust/database/mysql/projectdb.py
weblocust/database/mysql/resultdb.py
weblocust/database/mysql/taskdb.py
weblocust/database/redis/__init__.py
weblocust/database/redis/taskdb.py
weblocust/database/sqlalchemy/__init__.py
weblocust/database/sqlalchemy/projectdb.py
weblocust/database/sqlalchemy/resultdb.py
weblocust/database/sqlalchemy/sqlalchemybase.py
weblocust/database/sqlalchemy/taskdb.py
weblocust/database/sqlite/__init__.py
weblocust/database/sqlite/projectdb.py
weblocust/database/sqlite/resultdb.py
weblocust/database/sqlite/sqlitebase.py
weblocust/database/sqlite/taskdb.py
weblocust/fetcher/__init__.py
weblocust/fetcher/cookie_utils.py
weblocust/fetcher/phantomjs_fetcher.js
weblocust/fetcher/tornado_fetcher.py
weblocust/libs/ListIO.py
weblocust/libs/__init__.py
weblocust/libs/base_handler.py
weblocust/libs/bench.py
weblocust/libs/cleaners.py
weblocust/libs/counter.py
weblocust/libs/dataurl.py
weblocust/libs/log.py
weblocust/libs/multiprocessing_queue.py
weblocust/libs/pprint.py
weblocust/libs/response.py
weblocust/libs/result_dump.py
weblocust/libs/sample_handler.py
weblocust/libs/url.py
weblocust-1.0.2.dist-info/DESCRIPTION.rst
weblocust-1.0.2.dist-info/METADATA
weblocust-1.0.2.dist-info/RECORD
weblocust-1.0.2.dist-info/WHEEL
weblocust-1.0.2.dist-info/entry_points.txt
weblocust-1.0.2.dist-info/metadata.json
weblocust-1.0.2.dist-info/top_level.txt
