Metadata-Version: 2.0
Name: weblocust
Version: 1.0.2
Summary: A more Powerful Spider System in Python based on pyspider
Home-page: https://github.com/qiulimao/weblocust
Author: qiulimao
Author-email: qiulimao@getqiu.com
License: Apache License, Version 2.0
Keywords: scrapy crawler spider webui pyspider weblocust
Platform: UNKNOWN
Classifier: Development Status :: 4 - Beta
Classifier: Programming Language :: Python :: 2
Classifier: Programming Language :: Python :: 2.6
Classifier: Programming Language :: Python :: 2.7
Classifier: Programming Language :: Python :: 3
Classifier: Programming Language :: Python :: 3.3
Classifier: Programming Language :: Python :: 3.4
Classifier: License :: OSI Approved :: Apache Software License
Classifier: Intended Audience :: Developers
Classifier: Operating System :: OS Independent
Classifier: Environment :: Web Environment
Classifier: Topic :: Internet :: WWW/HTTP
Classifier: Topic :: Software Development :: Libraries :: Application Frameworks
Classifier: Topic :: Software Development :: Libraries :: Python Modules
Requires-Dist: Flask (>=0.10)
Requires-Dist: Flask-Login (>=0.2.11)
Requires-Dist: Jinja2 (>=2.7)
Requires-Dist: chardet (>=2.2)
Requires-Dist: click (>=3.3)
Requires-Dist: cssselect (>=0.9)
Requires-Dist: lxml
Requires-Dist: mkdocs
Requires-Dist: mongoengine
Requires-Dist: pycurl
Requires-Dist: pymongo
Requires-Dist: pyquery
Requires-Dist: requests (>=2.2)
Requires-Dist: six (>=1.5.0)
Requires-Dist: sqlalchemy
Requires-Dist: tornado (>=3.2)
Requires-Dist: u-msgpack-python (>=1.6)
Requires-Dist: wsgidav
Provides-Extra: all
Requires-Dist: SQLAlchemy (>=0.9.7); extra == 'all'
Requires-Dist: amqp (>=1.3.0); extra == 'all'
Requires-Dist: beanstalkc; extra == 'all'
Requires-Dist: elasticsearch; extra == 'all'
Requires-Dist: kombu; extra == 'all'
Requires-Dist: mysql-connector-python (>=1.2.2); extra == 'all'
Requires-Dist: pika (>=0.9.14); extra == 'all'
Requires-Dist: psycopg2; extra == 'all'
Requires-Dist: pymongo (>=2.7.2); extra == 'all'
Requires-Dist: redis; extra == 'all'
Provides-Extra: test
Requires-Dist: coverage; extra == 'test'
Requires-Dist: easywebdav; extra == 'test'
Requires-Dist: httpbin; extra == 'test'
Requires-Dist: pyproxy (>=0.1.6); extra == 'test'
Requires-Dist: unittest2 (>=0.5.1); extra == 'test'
